setup.cfg
setup.py
bike2cern/__init__.py
bike2cern/sync.py
bike2cern.egg-info/PKG-INFO
bike2cern.egg-info/SOURCES.txt
bike2cern.egg-info/dependency_links.txt
bike2cern.egg-info/entry_points.txt
bike2cern.egg-info/requires.txt
bike2cern.egg-info/top_level.txt