Metadata-Version: 1.1
Name: bike2cern
Version: 0.1.2
Summary: Sync rides from Strava to CERN Sharepoint
Home-page: https://github.com/matz-e/bike2cern
Author: Matthias Wolf
Author-email: m@sushinara.net
License: MIT
Download-URL: https://github.com/matz-e/bike2cern/archive/0.1.2.tar.gz
Keywords: strava
Platform: UNKNOWN
Classifier: Development Status :: 3 - Alpha
Classifier: Environment :: Console
Classifier: License :: OSI Approved :: MIT License
Classifier: Programming Language :: Python :: 3
